gradientcast/__init__.py
gradientcast/_base.py
gradientcast/_exceptions.py
gradientcast/_pandas.py
gradientcast/_version.py
gradientcast/client.py
gradientcast/py.typed
gradientcast/types.py
gradientcast-0.1.4.dist-info/licenses/LICENSE
gradientcast-0.1.4.dist-info/METADATA
gradientcast-0.1.4.dist-info/WHEEL
gradientcast-0.1.4.dist-info/top_level.txt
gradientcast-0.1.4.dist-info/RECORD
