Metadata-Version: 2.4
Name: gradientcast
Version: 0.1.4
Summary: Official Python SDK for GradientCast ML Services - Time series forecasting and anomaly detection
Author-email: GradientCast Team <support@gradientcast.com>
License-Expression: MIT
Project-URL: Homepage, https://gradientcast.com
Project-URL: Documentation, https://docs.gradientcast.com
Project-URL: Repository, https://github.com/GradientCast/gradientcast-sdk
Project-URL: Issues, https://github.com/GradientCast/gradientcast-sdk/issues
Project-URL: Changelog, https://github.com/GradientCast/gradientcast-sdk/blob/main/CHANGELOG.md
Keywords: time-series,forecasting,anomaly-detection,machine-learning,ml,api,sdk,gradientcast
Classifier: Development Status :: 4 - Beta
Classifier: Intended Audience :: Developers
Classifier: Intended Audience :: Science/Research
Classifier: Operating System :: OS Independent
Classifier: Programming Language :: Python :: 3
Classifier: Programming Language :: Python :: 3.8
Classifier: Programming Language :: Python :: 3.9
Classifier: Programming Language :: Python :: 3.10
Classifier: Programming Language :: Python :: 3.11
Classifier: Programming Language :: Python :: 3.12
Classifier: Topic :: Scientific/Engineering :: Artificial Intelligence
Classifier: Topic :: Software Development :: Libraries :: Python Modules
Classifier: Typing :: Typed
Requires-Python: >=3.8
License-File: LICENSE
Requires-Dist: requests>=2.25.0
Provides-Extra: pandas
Requires-Dist: pandas>=1.3.0; extra == "pandas"
Provides-Extra: dev
Requires-Dist: pytest>=7.0; extra == "dev"
Requires-Dist: pytest-cov>=4.0; extra == "dev"
Requires-Dist: responses>=0.23.0; extra == "dev"
Requires-Dist: mypy>=1.0; extra == "dev"
Requires-Dist: black>=23.0; extra == "dev"
Requires-Dist: ruff>=0.1.0; extra == "dev"
Requires-Dist: types-requests>=2.28.0; extra == "dev"
Provides-Extra: all
Requires-Dist: gradientcast[dev,pandas]; extra == "all"
Dynamic: license-file
